deep_geometry/__init__.py
deep_geometry/geom_scaler.py
deep_geometry/test_geom_scaler.py
deep_geometry/test_vectorizer.py
deep_geometry/vectorizer.py
deep_geometry-2.0.0.dist-info/LICENSE
deep_geometry-2.0.0.dist-info/METADATA
deep_geometry-2.0.0.dist-info/WHEEL
deep_geometry-2.0.0.dist-info/top_level.txt
deep_geometry-2.0.0.dist-info/RECORD
