Metadata-Version: 2.1
Name: deep-geometry
Version: 2.0.0
Summary: A python library for preprocessing geospatial vector geometries for use in deep learning
Home-page: https://github.com/SPINlab/deep-geometry
Author: Rein van 't Veer
Author-email: rein@geodan.nl
License: UNKNOWN
Platform: UNKNOWN
Classifier: Programming Language :: Python :: 3
Classifier: License :: OSI Approved :: MIT License
Classifier: Operating System :: OS Independent
Requires-Python: >=3.6
Requires-Dist: numpy
Requires-Dist: shapely
